lex_pdftotext-1.0.0.dist-info/licenses/LICENSE
src/__init__.py
src/extractors/__init__.py
src/extractors/base.py
src/extractors/pymupdf_extractor.py
src/extractors/table_extractor.py
src/formatters/__init__.py
src/formatters/json_formatter.py
src/formatters/markdown_formatter.py
src/formatters/table_formatter.py
src/lex_pdftotext/__init__.py
src/lex_pdftotext/cli.py
src/lex_pdftotext/py.typed
src/lex_pdftotext/extractors/__init__.py
src/lex_pdftotext/extractors/base.py
src/lex_pdftotext/extractors/pymupdf_extractor.py
src/lex_pdftotext/extractors/table_extractor.py
src/lex_pdftotext/formatters/__init__.py
src/lex_pdftotext/formatters/json_formatter.py
src/lex_pdftotext/formatters/markdown_formatter.py
src/lex_pdftotext/formatters/table_formatter.py
src/lex_pdftotext/processors/__init__.py
src/lex_pdftotext/processors/image_analyzer.py
src/lex_pdftotext/processors/metadata_parser.py
src/lex_pdftotext/processors/text_normalizer.py
src/lex_pdftotext/utils/__init__.py
src/lex_pdftotext/utils/cache.py
src/lex_pdftotext/utils/config.py
src/lex_pdftotext/utils/constants.py
src/lex_pdftotext/utils/exceptions.py
src/lex_pdftotext/utils/logger.py
src/lex_pdftotext/utils/patterns.py
src/lex_pdftotext/utils/timeout.py
src/lex_pdftotext/utils/validators.py
src/processors/__init__.py
src/processors/image_analyzer.py
src/processors/metadata_parser.py
src/processors/text_normalizer.py
src/utils/__init__.py
src/utils/cache.py
src/utils/config.py
src/utils/constants.py
src/utils/exceptions.py
src/utils/logger.py
src/utils/patterns.py
src/utils/timeout.py
src/utils/validators.py
lex_pdftotext-1.0.0.dist-info/METADATA
lex_pdftotext-1.0.0.dist-info/WHEEL
lex_pdftotext-1.0.0.dist-info/entry_points.txt
lex_pdftotext-1.0.0.dist-info/top_level.txt
lex_pdftotext-1.0.0.dist-info/RECORD
