Metadata-Version: 2.4
Name: lex-pdftotext
Version: 1.0.0
Summary: Extract and structure text from Brazilian legal PDF documents (PJe format)
Author-email: Felipe Bertrand Sardenberg Moulin <felipe.moulin.juiz@gmail.com>
License-Expression: MIT
Project-URL: Homepage, https://github.com/fbmoulin/pdftotext
Project-URL: Documentation, https://fbmoulin.github.io/pdftotext/
Project-URL: Repository, https://github.com/fbmoulin/pdftotext
Project-URL: Issues, https://github.com/fbmoulin/pdftotext/issues
Project-URL: Changelog, https://github.com/fbmoulin/pdftotext/blob/main/CHANGELOG.md
Keywords: pdf,text extraction,legal documents,brazilian law,pje,document processing,rag,markdown,lex-intelligentia
Classifier: Development Status :: 5 - Production/Stable
Classifier: Intended Audience :: Legal Industry
Classifier: Intended Audience :: Developers
Classifier: Operating System :: OS Independent
Classifier: Programming Language :: Python :: 3
Classifier: Programming Language :: Python :: 3.10
Classifier: Programming Language :: Python :: 3.11
Classifier: Programming Language :: Python :: 3.12
Classifier: Topic :: Text Processing
Classifier: Topic :: Office/Business
Classifier: Topic :: Software Development :: Libraries :: Python Modules
Requires-Python: >=3.10
License-File: LICENSE
Requires-Dist: pymupdf>=1.23.0
Requires-Dist: pdfplumber>=0.10.0
Requires-Dist: click>=8.0.0
Requires-Dist: python-dotenv>=1.0.0
Requires-Dist: tqdm>=4.65.0
Requires-Dist: PyYAML>=6.0
Provides-Extra: vision
Requires-Dist: google-generativeai>=0.3.0; extra == "vision"
Requires-Dist: Pillow>=10.0.0; extra == "vision"
Provides-Extra: gui
Requires-Dist: pywebview>=4.0; extra == "gui"
Provides-Extra: dev
Requires-Dist: black>=24.0.0; extra == "dev"
Requires-Dist: isort>=5.13.0; extra == "dev"
Requires-Dist: flake8>=7.0.0; extra == "dev"
Requires-Dist: ruff>=0.6.0; extra == "dev"
Requires-Dist: mypy>=1.11.0; extra == "dev"
Requires-Dist: types-PyYAML>=6.0.0; extra == "dev"
Requires-Dist: pytest>=8.3.0; extra == "dev"
Requires-Dist: pytest-cov>=6.0.0; extra == "dev"
Requires-Dist: pytest-mock>=3.14.0; extra == "dev"
Requires-Dist: pytest-asyncio>=0.24.0; extra == "dev"
Requires-Dist: pytest-xdist>=3.6.0; extra == "dev"
Requires-Dist: sphinx>=7.4.0; extra == "dev"
Requires-Dist: sphinx-rtd-theme>=2.0.0; extra == "dev"
Requires-Dist: pre-commit>=3.8.0; extra == "dev"
Requires-Dist: bandit>=1.7.0; extra == "dev"
Requires-Dist: radon>=6.0.0; extra == "dev"
Requires-Dist: build>=1.0.0; extra == "dev"
Requires-Dist: twine>=5.0.0; extra == "dev"
Provides-Extra: build
Requires-Dist: pyinstaller>=6.0.0; extra == "build"
Provides-Extra: all
Requires-Dist: lex-pdftotext[build,dev,gui,vision]; extra == "all"
Dynamic: license-file
